[
{"id":1,"priority":1,"action":{"type":"redirect","redirect":{"transform":{"queryTransform":{"removeParams":["advn","alid","bb","from","fvj","jsa","oc","pub","sal","sjdu","tk","vjk","vjs","xkcb","xpse"]}}}},"condition":{"resourceTypes":["main_frame","sub_frame","xmlhttprequest"],"requestDomains":["indeed.com"]}},
{"id":2,"priority":1,"action":{"type":"redirect","redirect":{"transform":{"queryTransform":{"removeParams":["af","aff_request_id","algo_expid","algo_pvid","btsid","cv","dp","gps-id","mall_affr","pvid","sk","terminal_id","ws_ab_test"]}}}},"condition":{"resourceTypes":["main_frame","sub_frame","xmlhttprequest"],"requestDomains":["aliexpress.*"]}},
{"action":{"redirect":{"transform":{"queryTransform":{"removeParams":["$deep_link","$original_url","%243p","%24deep_link","%24original_url","?$deep_link","_branch_match_id","cId","chainedPosts","correlation_id","iId","post_fullname","post_index","rdt","ref","ref_campaign","ref_source","share_id","st","type"]}}},"type":"redirect"},"condition":{"requestDomains":["reddit.com"],"resourceTypes":["main_frame","sub_frame","xmlhttprequest"]},"id":3,"priority":1},
{"id":4,"priority":1,"action":{"type":"redirect","redirect":{"transform":{"queryTransform":{"removeParams":["CMP_ID","CMP_SKU","INT_ID","MER","fl","iv_","k_clickid","mr:adType","mr:device","mr:trackingCode","rmatt","ti"]}}}},"condition":{"resourceTypes":["main_frame","sub_frame","xmlhttprequest"],"requestDomains":["backcountry.com"]}},
{"action":{"redirect":{"transform":{"queryTransform":{"removeParams":["__tppBottom","_t","algo_exp_id","curPageLogUid","cv","dp","gatewayAdapt","gps-id","initiative_id","pdp_ext_f","pdp_npi","pdp_pi","terminal_id","tt","utparam","utparam-url"]}}},"type":"redirect"},"condition":{"requestDomains":["aliexpress.com"],"resourceTypes":["main_frame","sub_frame","xmlhttprequest"]},"id":5,"priority":1},
{"id":6,"priority":1,"action":{"type":"redirect","redirect":{"transform":{"queryTransform":{"removeParams":["RelatedAssetID","RelatedAssetType","discoverPageSessionInfo","gameSearchSessionInfo","gameSetTargetId","isAd","nativeAdData","numberOfLoadedTiles","refPageId","sortPos","treatmentType","universeId"]}}}},"condition":{"resourceTypes":["main_frame","sub_frame","xmlhttprequest"],"requestDomains":["roblox.com"]}},
{"action":{"redirect":{"transform":{"queryTransform":{"removeParams":["algodoc","checkout_entry_point","fellback|","impression_id","login_source","module|","pool|","ref_page","referringSource","region|","req_id|","sgrp","smid","variant|"]}}},"type":"redirect"},"condition":{"requestDomains":["nytimes.com"],"resourceTypes":["main_frame","sub_frame","xmlhttprequest"]},"id":7,"priority":1},
{"id":8,"priority":1,"action":{"type":"redirect","redirect":{"transform":{"queryTransform":{"removeParams":["afp","bta","context_alg","context_referrer","context_type","cxd_token","funnel","is_pro","pckg_id","ref_ctx_id","source"]}}}},"condition":{"resourceTypes":["main_frame","sub_frame","xmlhttprequest"],"requestDomains":["fiverr.com"]}},
{"action":{"redirect":{"transform":{"queryTransform":{"removeParams":["blog_photo","bp1","bp2","bp7","cellid","ciphertext","g","g_f","jumptoqzone","loginfrom","res_uin","subid","subtype"]}}},"type":"redirect"},"condition":{"requestDomains":["qzone.qq.com"],"resourceTypes":["main_frame","sub_frame","xmlhttprequest"]},"id":9,"priority":1},
{"action":{"redirect":{"transform":{"queryTransform":{"removeParams":["t-id","t-referrer_browse_type","t-referrer_category_id","t-referrer_page_type","t-referrer_request_id","t-referrer_search_query","t-referrer_search_query_source","t-referrer_sort_by","t-referrer_source","t-source","t-tap_index"]}}},"type":"redirect"},"condition":{"resourceTypes":["main_frame","sub_frame","xmlhttprequest"],"urlFilter":"||carousell."},"id":10,"priority":1},
{"id":11,"priority":1,"action":{"type":"redirect","redirect":{"transform":{"queryTransform":{"removeParams":["clickTrackInfo","abid","pvid","ad_src","spm","src","from","scm","pa","pid_pvid","did","mp","cid","impsrc","pos"]}}}},"condition":{"regexFilter":"^https?:\\/\\/(?:[a-z0-9-]+\\.)*?lazada\\.(com|co\\.th|co\\.id|com\\.my|com\\.ph|sg|vn)","resourceTypes":["sub_frame","main_frame","xmlhttprequest"]}},
{"action":{"redirect":{"transform":{"queryTransform":{"removeParams":["ad","c_ad","c_app","c_app_from","c_bm","c_dt","c_ex","c_id","c_sys","c_u","c_ut","c_ver","c_wh","client_e","client_m","client_t","clientusertype","soft","trackid","ver"]}}},"type":"redirect"},"condition":{"requestDomains":["dvdfab.org"],"resourceTypes":["main_frame","sub_frame","xmlhttprequest"]},"id":12,"priority":1},
{"action":{"redirect":{"transform":{"queryTransform":{"removeParams":["adj_adgroup","adj_campaign","adj_creative","adj_t","adp_cid","adp_oid","aid","campid","cid","crid","plid","shopId","sid","source"]}}},"type":"redirect"},"condition":{"requestDomains":["teknosa.com"],"resourceTypes":["main_frame","sub_frame","xmlhttprequest"]},"id":13,"priority":1},
{"action":{"redirect":{"transform":{"queryTransform":{"removeParams":["ad","c_app","c_app_from","c_bm","c_dt","c_sys","c_try","c_ut","c_ver","c_wh","soft","trackid"]}}},"type":"redirect"},"condition":{"requestDomains":["streamfab.jp"],"resourceTypes":["main_frame","sub_frame","xmlhttprequest"]},"id":14,"priority":1},
{"action":{"redirect":{"transform":{"queryTransform":{"removeParams":["__rr","abt_att","advert","asb","asb2","avtc","avte","avts","from_sku","from_url","keywords","partner"]}}},"type":"redirect"},"condition":{"requestDomains":["ozon.ru"],"resourceTypes":["main_frame","sub_frame","xmlhttprequest"]},"id":15,"priority":1},
{"id":16,"priority":1,"action":{"type":"redirect","redirect":{"transform":{"queryTransform":{"removeParams":["srctype","ret","ici","_t","tag_ids","is_manual_change_site","adp","scici","icn","rep","userpath"]}}}},"condition":{"resourceTypes":["xmlhttprequest","sub_frame","main_frame"],"requestDomains":["shein.com","shein.co.uk"]}},
{"action":{"redirect":{"transform":{"queryTransform":{"removeParams":["/^ign-.*","/ign-.*","afid","app","cid","ct","ctx_brand","fnode","ign-itsc[a-z]+","mttn3pid","mttnagencyid","mttncc","mttnpid","mttnsiteid","mttnsubad","mttnsubkw","mttnsubplmnt","pt"]}}},"type":"redirect"},"condition":{"requestDomains":["apple.com"],"resourceTypes":["main_frame","sub_frame","xmlhttprequest"]},"id":17,"priority":1},
{"id":18,"priority":1,"action":{"type":"redirect","redirect":{"transform":{"queryTransform":{"removeParams":["t-source","t-referrer_source","t-referrer_browse_type","t-referrer_category_id","t-id","t-referrer_page_type","t-referrer_search_query","t-referrer_search_query_source","t-referrer_request_id","t-referrer_sort_by","t-tap_index"]}}}},"condition":{"resourceTypes":["xmlhttprequest","sub_frame","main_frame"],"requestDomains":["carousell.com"]}},
{"action":{"redirect":{"transform":{"queryTransform":{"removeParams":["adblock","compact_view","dnt","domain","feature","geoip_country","language","loid","loid_created","mweb_loid","mweb_loid_create","mweb_user_name","reddaid","referrer_domain","referrer_url","session_id","sr_id","sr_name","tags","user_agent"]}}},"type":"redirect"},"condition":{"requestDomains":["reddit.app.link"],"resourceTypes":["main_frame","sub_frame","xmlhttprequest"]},"id":19,"priority":1},
{"action":{"redirect":{"transform":{"queryTransform":{"removeParams":["CollectionId","adj_adgroup","adj_adnomia_click_id","adj_campaign","adj_creative","adj_deeplink","adj_event_callback_dn2j7g_5mdnim","adj_install_callback","adjust_deeplink","pd","pfx","pt"]}}},"type":"redirect"},"condition":{"requestDomains":["adj.st"],"resourceTypes":["main_frame","sub_frame","xmlhttprequest"]},"id":20,"priority":1},
{"action":{"redirect":{"transform":{"queryTransform":{"removeParams":["bh","bw","domComplete","domContentLoadedEventEnd","domContentLoadedEventStart","domInteractive","domLoading","ln","loadEventEnd","loadEventStart","ls","navigationStart","os","pid","requestStart","responseEnd","responseStart","sr","ts"]}}},"type":"redirect"},"condition":{"resourceTypes":["main_frame","sub_frame","xmlhttprequest"],"urlFilter":"||lcs.naver.com/m?u="},"id":21,"priority":1},
{"action":{"redirect":{"transform":{"queryTransform":{"removeParams":["cmnhd_ref","news_ref","ra","rd","ref","rf","rp","track","transit_from","transition_id","transition_type"]}}},"type":"redirect"},"condition":{"requestDomains":["nicovideo.jp"],"resourceTypes":["main_frame","sub_frame","xmlhttprequest"]},"id":22,"priority":1},
{"action":{"redirect":{"transform":{"queryTransform":{"removeParams":["bkt","e","flashvars","pccenter_fr","pltfm","pos","r_area","r_source","s_source","source","sr","ssra","ssrt","stype","vfrm","vfrmblk","vfrmrst"]}}},"type":"redirect"},"condition":{"requestDomains":["iqiyi.com"],"resourceTypes":["main_frame","sub_frame","xmlhttprequest"]},"id":23,"priority":1},
{"id":24,"priority":1,"action":{"type":"redirect","redirect":{"transform":{"queryTransform":{"removeParams":["numberOfLoadedTiles","treatmentType","gameSearchSessionInfo","RelatedAssetID","nativeAdData","universeId","gameSetTargetId","discoverPageSessionInfo","isAd","RelatedAssetType","sortPos"]}}}},"condition":{"resourceTypes":["xmlhttprequest","sub_frame","main_frame"],"requestDomains":["www.roblox.com"]}},
{"action":{"redirect":{"transform":{"queryTransform":{"removeParams":["at_bbc_team","at_campaign","at_campaign_type","at_creation","at_custom1","at_custom2","at_custom3","at_custom4","at_format","at_identifier","at_link_id","at_link_origin","at_link_type","at_ptr_name","at_type","at_variant","facebook_page","pinned_post_asset_id","pinned_post_locator","pinned_post_type"]}}},"type":"redirect"},"condition":{"resourceTypes":["main_frame","sub_frame","xmlhttprequest"],"urlFilter":"||bbc."},"id":25,"priority":1},
{"id":26,"priority":1,"action":{"type":"redirect","redirect":{"transform":{"queryTransform":{"removeParams":["app_platform","app_platformdoc","app_version","app_versiondoc","apptime","apptimedoc","appuid","appuiddoc","doc","share_from_user_hidden","share_from_user_hiddendoc","xhsshare","xhssharedoc"]}}}},"condition":{"resourceTypes":["main_frame","sub_frame","xmlhttprequest"],"requestDomains":["xiaohongshu.com"]}}
]
